context_converter-1.1.1.dist-info/METADATA
context_converter-1.1.1.dist-info/WHEEL
context_converter-1.1.1.dist-info/licenses/LICENSE
context_converter/__init__.py
context_converter/converter.py
context_converter/download_jina.py
context_converter/formatter.py
context_converter/main.py
context_converter/utils.py
context_converter-1.1.1.dist-info/RECORD
