Metadata-Version: 2.1
Name: context-converter
Version: 1.1.1
Summary: Convert HTML to Markdown using Regex, BeautifulSoup4, and filter repeating characters with Jina Embeddings and a similarity threshold.
Author-Email: Daethyra <109057945+Daethyra@users.noreply.github.com>
License: MIT
Requires-Python: >=3.10
Requires-Dist: beautifulsoup4>=4.12.2
Requires-Dist: markdownify>=0.11.6
Requires-Dist: transformers>=4.36.2
Requires-Dist: torch>=2.1.2
Requires-Dist: aiofiles>=23.2.1
Requires-Dist: asyncio>=3.4.3
